{
  "meta": {
    "total_count": 51,
    "IAM_unidade_id": "320",
    "IAM_dominio_id": "310",
    "limit": "3000",
    "offset": "0"
  },
  "objects": [
    {
      "id": "165634",
      "IAM_dominio_id": "310",
      "IAM_unidade_id": "320",
      "IAM_usuario_id": "88",
      "VIA_cliente_id": "118",
      "datahora_cadastro": "2023-04-19 15:57:24",
      "datahora_desativacao": null,
      "nome": "teste 1",
      "descricao": "xx",
      "observacao": "xx",
      "orcamentos": [
        "11467"
      ],
      "status": "Vendido"
    },
    {
      "id": "165664",
      "IAM_dominio_id": "310",
      "IAM_unidade_id": "320",
      "IAM_usuario_id": "88",
      "VIA_cliente_id": "118",
      "datahora_cadastro": "2023-04-21 11:47:56",
      "datahora_desativacao": null,
      "nome": "teste frentes",
      "descricao": "xx",
      "observacao": "xx",
      "orcamentos": [
        "11495"
      ],
      "status": "Vendido"
    },
    {
      "id": "165665",
      "IAM_dominio_id": "310",
      "IAM_unidade_id": "320",
      "IAM_usuario_id": "88",
      "VIA_cliente_id": "118",
      "datahora_cadastro": "2023-04-21 14:08:26",
      "datahora_desativacao": null,
      "nome": "TESTE FURO GAV",
      "descricao": "XX",
      "observacao": "XX",
      "orcamentos": [
        "11496"
      ],
      "status": "Vendido"
    },
    {
      "id": "165721",
      "IAM_dominio_id": "310",
      "IAM_unidade_id": "320",
      "IAM_usuario_id": "88",
      "VIA_cliente_id": "118",
      "datahora_cadastro": "2023-04-26 11:57:32",
      "datahora_desativacao": null,
      "nome": "TESTE 2604",
      "descricao": "XX",
      "observacao": "XX",
      "orcamentos": [
        "11550"
      ],
      "status": "Vendido"
    },
    {
      "id": "165804",
      "IAM_dominio_id": "310",
      "IAM_unidade_id": "320",
      "IAM_usuario_id": "88",
      "VIA_cliente_id": "118",
      "datahora_cadastro": "2023-04-28 19:49:32",
      "datahora_desativacao": null,
      "nome": "teste2804",
      "descricao": "xx",
      "observacao": "xx",
      "orcamentos": [
        "11630"
      ],
      "status": "Vendido"
    },
    {
      "id": "165861",
      "IAM_dominio_id": "310",
      "IAM_unidade_id": "320",
      "IAM_usuario_id": "7704",
      "VIA_cliente_id": "118",
      "datahora_cadastro": "2023-05-03 13:30:00",
      "datahora_desativacao": null,
      "nome": "Teste - prat",
      "descricao": "",
      "observacao": "",
      "orcamentos": [
        "11687"
      ],
      "status": "Vendido"
    },
    {
      "id": "165862",
      "IAM_dominio_id": "310",
      "IAM_unidade_id": "320",
      "IAM_usuario_id": "9477",
      "VIA_cliente_id": "118",
      "datahora_cadastro": "2023-05-03 13:48:46",
      "datahora_desativacao": null,
      "nome": "Teste furação",
      "descricao": "",
      "observacao": "",
      "orcamentos": [
        "11688"
      ],
      "status": "Vendido"
    },
    {
      "id": "165863",
      "IAM_dominio_id": "310",
      "IAM_unidade_id": "320",
      "IAM_usuario_id": "9477",
      "VIA_cliente_id": "118",
      "datahora_cadastro": "2023-05-03 13:56:45",
      "datahora_desativacao": null,
      "nome": "Teste furação 1",
      "descricao": "",
      "observacao": "",
      "orcamentos": [
        "11689"
      ],
      "status": "Vendido"
    },
    {
      "id": "165870",
      "IAM_dominio_id": "310",
      "IAM_unidade_id": "320",
      "IAM_usuario_id": "9477",
      "VIA_cliente_id": "118",
      "datahora_cadastro": "2023-05-03 15:51:21",
      "datahora_desativacao": null,
      "nome": "teste furação 2",
      "descricao": "",
      "observacao": "",
      "orcamentos": [
        "11696"
      ],
      "status": "Vendido"
    },
    {
      "id": "165877",
      "IAM_dominio_id": "310",
      "IAM_unidade_id": "320",
      "IAM_usuario_id": "8633",
      "VIA_cliente_id": "118",
      "datahora_cadastro": "2023-05-03 16:30:39",
      "datahora_desativacao": null,
      "nome": "rodrigo_teste_gab_2g",
      "descricao": "xxx",
      "observacao": "xxx",
      "orcamentos": [
        "11701"
      ],
      "status": "Orçamento"
    },
    {
      "id": "165880",
      "IAM_dominio_id": "310",
      "IAM_unidade_id": "320",
      "IAM_usuario_id": "9477",
      "VIA_cliente_id": "118",
      "datahora_cadastro": "2023-05-03 17:01:03",
      "datahora_desativacao": null,
      "nome": "teste furação 3",
      "descricao": "",
      "observacao": "",
      "orcamentos": [
        "11704"
      ],
      "status": "Vendido"
    },
    {
      "id": "165883",
      "IAM_dominio_id": "310",
      "IAM_unidade_id": "320",
      "IAM_usuario_id": "9477",
      "VIA_cliente_id": "118",
      "datahora_cadastro": "2023-05-03 17:42:17",
      "datahora_desativacao": null,
      "nome": "teste furação 4",
      "descricao": "",
      "observacao": "",
      "orcamentos": [
        "11707",
        "11708"
      ],
      "status": "Vendido"
    },
    {
      "id": "165884",
      "IAM_dominio_id": "310",
      "IAM_unidade_id": "320",
      "IAM_usuario_id": "7704",
      "VIA_cliente_id": "118",
      "datahora_cadastro": "2023-05-03 17:52:18",
      "datahora_desativacao": null,
      "nome": "teste basc",
      "descricao": "",
      "observacao": ""
    },
    {
      "id": "165900",
      "IAM_dominio_id": "310",
      "IAM_unidade_id": "320",
      "IAM_usuario_id": "9477",
      "VIA_cliente_id": "118",
      "datahora_cadastro": "2023-05-04 11:22:35",
      "datahora_desativacao": null,
      "nome": "teste furação 5",
      "descricao": "",
      "observacao": "",
      "orcamentos": [
        "11724"
      ],
      "status": "Vendido"
    },
    {
      "id": "165906",
      "IAM_dominio_id": "310",
      "IAM_unidade_id": "320",
      "IAM_usuario_id": "7704",
      "VIA_cliente_id": "118",
      "datahora_cadastro": "2023-05-04 12:21:18",
      "datahora_desativacao": null,
      "nome": "teste basc",
      "descricao": "",
      "observacao": "",
      "orcamentos": [
        "11731"
      ],
      "status": "Vendido"
    },
    {
      "id": "165907",
      "IAM_dominio_id": "310",
      "IAM_unidade_id": "320",
      "IAM_usuario_id": "7704",
      "VIA_cliente_id": "118",
      "datahora_cadastro": "2023-05-04 12:26:52",
      "datahora_desativacao": null,
      "nome": "teste basculante",
      "descricao": "",
      "observacao": "",
      "orcamentos": [
        "11732"
      ],
      "status": "Vendido"
    },
    {
      "id": "165908",
      "IAM_dominio_id": "310",
      "IAM_unidade_id": "320",
      "IAM_usuario_id": "7704",
      "VIA_cliente_id": "118",
      "datahora_cadastro": "2023-05-04 12:45:28",
      "datahora_desativacao": null,
      "nome": "TESTE BASCULANTE 2",
      "descricao": "",
      "observacao": "",
      "orcamentos": [
        "11733"
      ],
      "status": "Vendido"
    },
    {
      "id": "165910",
      "IAM_dominio_id": "310",
      "IAM_unidade_id": "320",
      "IAM_usuario_id": "7704",
      "VIA_cliente_id": "118",
      "datahora_cadastro": "2023-05-04 13:01:05",
      "datahora_desativacao": null,
      "nome": "teste basculante 3",
      "descricao": "",
      "observacao": "",
      "orcamentos": [
        "11735"
      ],
      "status": "Vendido"
    },
    {
      "id": "165911",
      "IAM_dominio_id": "310",
      "IAM_unidade_id": "320",
      "IAM_usuario_id": "7704",
      "VIA_cliente_id": "118",
      "datahora_cadastro": "2023-05-04 13:07:04",
      "datahora_desativacao": null,
      "nome": "teste basculante 4",
      "descricao": "",
      "observacao": "",
      "orcamentos": [
        "11736"
      ],
      "status": "Vendido"
    },
    {
      "id": "165914",
      "IAM_dominio_id": "310",
      "IAM_unidade_id": "320",
      "IAM_usuario_id": "7704",
      "VIA_cliente_id": "118",
      "datahora_cadastro": "2023-05-04 13:19:31",
      "datahora_desativacao": null,
      "nome": "teste basculante 5",
      "descricao": "",
      "observacao": "",
      "orcamentos": [
        "11738"
      ],
      "status": "Vendido"
    },
    {
      "id": "165916",
      "IAM_dominio_id": "310",
      "IAM_unidade_id": "320",
      "IAM_usuario_id": "7704",
      "VIA_cliente_id": "118",
      "datahora_cadastro": "2023-05-04 13:45:17",
      "datahora_desativacao": null,
      "nome": "teste basculante 6",
      "descricao": "",
      "observacao": "",
      "orcamentos": [
        "11740"
      ],
      "status": "Vendido"
    },
    {
      "id": "165922",
      "IAM_dominio_id": "310",
      "IAM_unidade_id": "320",
      "IAM_usuario_id": "7704",
      "VIA_cliente_id": "118",
      "datahora_cadastro": "2023-05-04 13:54:44",
      "datahora_desativacao": null,
      "nome": "teste basculante 7",
      "descricao": "",
      "observacao": "",
      "orcamentos": [
        "11746"
      ],
      "status": "Vendido"
    },
    {
      "id": "165923",
      "IAM_dominio_id": "310",
      "IAM_unidade_id": "320",
      "IAM_usuario_id": "7704",
      "VIA_cliente_id": "118",
      "datahora_cadastro": "2023-05-04 13:59:49",
      "datahora_desativacao": null,
      "nome": "teste basculante 7",
      "descricao": "",
      "observacao": "",
      "orcamentos": [
        "11747"
      ],
      "status": "Vendido"
    },
    {
      "id": "165925",
      "IAM_dominio_id": "310",
      "IAM_unidade_id": "320",
      "IAM_usuario_id": "7704",
      "VIA_cliente_id": "118",
      "datahora_cadastro": "2023-05-04 14:04:18",
      "datahora_desativacao": null,
      "nome": "teste basculante 8",
      "descricao": "",
      "observacao": "",
      "orcamentos": [
        "11749"
      ],
      "status": "Vendido"
    },
    {
      "id": "165927",
      "IAM_dominio_id": "310",
      "IAM_unidade_id": "320",
      "IAM_usuario_id": "7704",
      "VIA_cliente_id": "118",
      "datahora_cadastro": "2023-05-04 14:07:14",
      "datahora_desativacao": null,
      "nome": "teste basculante 9",
      "descricao": "",
      "observacao": "",
      "orcamentos": [
        "11751"
      ],
      "status": "Vendido"
    },
    {
      "id": "165932",
      "IAM_dominio_id": "310",
      "IAM_unidade_id": "320",
      "IAM_usuario_id": "7704",
      "VIA_cliente_id": "118",
      "datahora_cadastro": "2023-05-04 15:12:16",
      "datahora_desativacao": null,
      "nome": "teste basculante 10",
      "descricao": "",
      "observacao": "",
      "orcamentos": [
        "11756"
      ],
      "status": "Vendido"
    },
    {
      "id": "165941",
      "IAM_dominio_id": "310",
      "IAM_unidade_id": "320",
      "IAM_usuario_id": "7704",
      "VIA_cliente_id": "118",
      "datahora_cadastro": "2023-05-04 17:15:45",
      "datahora_desativacao": null,
      "nome": "teste hk xs",
      "descricao": "",
      "observacao": "",
      "orcamentos": [
        "11766"
      ],
      "status": "Vendido"
    },
    {
      "id": "165944",
      "IAM_dominio_id": "310",
      "IAM_unidade_id": "320",
      "IAM_usuario_id": "7704",
      "VIA_cliente_id": "118",
      "datahora_cadastro": "2023-05-04 17:52:11",
      "datahora_desativacao": null,
      "nome": "TESTE DOBRADIÇA",
      "descricao": "",
      "observacao": "",
      "orcamentos": [
        "11769"
      ],
      "status": "Vendido"
    },
    {
      "id": "165945",
      "IAM_dominio_id": "310",
      "IAM_unidade_id": "320",
      "IAM_usuario_id": "7704",
      "VIA_cliente_id": "118",
      "datahora_cadastro": "2023-05-04 17:58:32",
      "datahora_desativacao": null,
      "nome": "teste dobradiça bascs",
      "descricao": "",
      "observacao": "",
      "orcamentos": [
        "11770"
      ],
      "status": "Vendido"
    },
    {
      "id": "166008",
      "IAM_dominio_id": "310",
      "IAM_unidade_id": "320",
      "IAM_usuario_id": "7704",
      "VIA_cliente_id": "118",
      "datahora_cadastro": "2023-05-08 15:40:41",
      "datahora_desativacao": null,
      "nome": "balcao - furações",
      "descricao": "",
      "observacao": "",
      "orcamentos": [
        "11835"
      ],
      "status": "Vendido"
    },
    {
      "id": "166014",
      "IAM_dominio_id": "310",
      "IAM_unidade_id": "320",
      "IAM_usuario_id": "7704",
      "VIA_cliente_id": "118",
      "datahora_cadastro": "2023-05-08 17:43:40",
      "datahora_desativacao": null,
      "nome": "teste - rasgo",
      "descricao": "",
      "observacao": "",
      "orcamentos": [
        "11841"
      ],
      "status": "Vendido"
    },
    {
      "id": "166069",
      "IAM_dominio_id": "310",
      "IAM_unidade_id": "320",
      "IAM_usuario_id": "14",
      "VIA_cliente_id": "118",
      "datahora_cadastro": "2023-05-10 15:22:38",
      "datahora_desativacao": null,
      "nome": "Gaveteiro 2 gav",
      "descricao": "Gaveteiro 2 gav",
      "observacao": "Gaveteiro 2 gav",
      "orcamentos": [
        "11898"
      ],
      "status": "Vendido"
    },
    {
      "id": "166084",
      "IAM_dominio_id": "310",
      "IAM_unidade_id": "320",
      "IAM_usuario_id": "7704",
      "VIA_cliente_id": "118",
      "datahora_cadastro": "2023-05-11 15:27:07",
      "datahora_desativacao": null,
      "nome": "TESTE - canto L",
      "descricao": "",
      "observacao": "",
      "orcamentos": [
        "11912",
        "11914"
      ],
      "status": "Vendido"
    },
    {
      "id": "166096",
      "IAM_dominio_id": "310",
      "IAM_unidade_id": "320",
      "IAM_usuario_id": "7704",
      "VIA_cliente_id": "118",
      "datahora_cadastro": "2023-05-11 16:42:16",
      "datahora_desativacao": null,
      "nome": "teste - canto L",
      "descricao": "",
      "observacao": "",
      "orcamentos": [
        "11925"
      ],
      "status": "Vendido"
    },
    {
      "id": "166097",
      "IAM_dominio_id": "310",
      "IAM_unidade_id": "320",
      "IAM_usuario_id": "7704",
      "VIA_cliente_id": "118",
      "datahora_cadastro": "2023-05-11 16:44:49",
      "datahora_desativacao": null,
      "nome": "TESTE - canto L 3",
      "descricao": "",
      "observacao": "",
      "orcamentos": [
        "11926"
      ],
      "status": "Vendido"
    },
    {
      "id": "166105",
      "IAM_dominio_id": "310",
      "IAM_unidade_id": "320",
      "IAM_usuario_id": "8633",
      "VIA_cliente_id": "118",
      "datahora_cadastro": "2023-05-12 11:22:43",
      "datahora_desativacao": null,
      "nome": "teste_gab_2portas",
      "descricao": "xxx",
      "observacao": "xxx",
      "orcamentos": [
        "11933"
      ],
      "status": "Vendido"
    },
    {
      "id": "166120",
      "IAM_dominio_id": "310",
      "IAM_unidade_id": "320",
      "IAM_usuario_id": "7704",
      "VIA_cliente_id": "118",
      "datahora_cadastro": "2023-05-15 10:35:00",
      "datahora_desativacao": null,
      "nome": "TESTE - Canto L 1",
      "descricao": "",
      "observacao": "",
      "orcamentos": [
        "11947"
      ],
      "status": "Vendido"
    },
    {
      "id": "166121",
      "IAM_dominio_id": "310",
      "IAM_unidade_id": "320",
      "IAM_usuario_id": "7704",
      "VIA_cliente_id": "118",
      "datahora_cadastro": "2023-05-15 11:12:00",
      "datahora_desativacao": null,
      "nome": "TESTE - Canto L 2",
      "descricao": "",
      "observacao": "",
      "orcamentos": [
        "11948"
      ],
      "status": "Vendido"
    },
    {
      "id": "166126",
      "IAM_dominio_id": "310",
      "IAM_unidade_id": "320",
      "IAM_usuario_id": "7704",
      "VIA_cliente_id": "118",
      "datahora_cadastro": "2023-05-15 13:30:11",
      "datahora_desativacao": null,
      "nome": "TESTE - Canto L 3",
      "descricao": "",
      "observacao": "",
      "orcamentos": [
        "11953"
      ],
      "status": "Vendido"
    },
    {
      "id": "166127",
      "IAM_dominio_id": "310",
      "IAM_unidade_id": "320",
      "IAM_usuario_id": "7704",
      "VIA_cliente_id": "118",
      "datahora_cadastro": "2023-05-15 13:39:01",
      "datahora_desativacao": null,
      "nome": "TESTE - Canto L 4",
      "descricao": "",
      "observacao": "",
      "orcamentos": [
        "11954"
      ],
      "status": "Vendido"
    },
    {
      "id": "166128",
      "IAM_dominio_id": "310",
      "IAM_unidade_id": "320",
      "IAM_usuario_id": "7704",
      "VIA_cliente_id": "118",
      "datahora_cadastro": "2023-05-15 13:55:48",
      "datahora_desativacao": null,
      "nome": "TESTE - canto L 5",
      "descricao": "",
      "observacao": "",
      "orcamentos": [
        "11955"
      ],
      "status": "Vendido"
    },
    {
      "id": "166129",
      "IAM_dominio_id": "310",
      "IAM_unidade_id": "320",
      "IAM_usuario_id": "7704",
      "VIA_cliente_id": "118",
      "datahora_cadastro": "2023-05-15 14:09:27",
      "datahora_desativacao": null,
      "nome": "TESTE - Canto L 6",
      "descricao": "",
      "observacao": "",
      "orcamentos": [
        "11956"
      ],
      "status": "Vendido"
    },
    {
      "id": "166131",
      "IAM_dominio_id": "310",
      "IAM_unidade_id": "320",
      "IAM_usuario_id": "7704",
      "VIA_cliente_id": "118",
      "datahora_cadastro": "2023-05-15 14:26:34",
      "datahora_desativacao": null,
      "nome": "teste Canto L 7",
      "descricao": "",
      "observacao": "",
      "orcamentos": [
        "11958"
      ],
      "status": "Vendido"
    },
    {
      "id": "166133",
      "IAM_dominio_id": "310",
      "IAM_unidade_id": "320",
      "IAM_usuario_id": "7704",
      "VIA_cliente_id": "118",
      "datahora_cadastro": "2023-05-15 14:33:25",
      "datahora_desativacao": null,
      "nome": "TESTE - Canto L 8",
      "descricao": "",
      "observacao": "",
      "orcamentos": [
        "11960"
      ],
      "status": "Vendido"
    },
    {
      "id": "166134",
      "IAM_dominio_id": "310",
      "IAM_unidade_id": "320",
      "IAM_usuario_id": "7704",
      "VIA_cliente_id": "118",
      "datahora_cadastro": "2023-05-15 14:52:05",
      "datahora_desativacao": null,
      "nome": "TESTE - Canto L 9",
      "descricao": "",
      "observacao": "",
      "orcamentos": [
        "11961"
      ],
      "status": "Vendido"
    },
    {
      "id": "166135",
      "IAM_dominio_id": "310",
      "IAM_unidade_id": "320",
      "IAM_usuario_id": "7704",
      "VIA_cliente_id": "118",
      "datahora_cadastro": "2023-05-15 14:54:59",
      "datahora_desativacao": null,
      "nome": "TESTE - Canto L 10",
      "descricao": "",
      "observacao": "",
      "orcamentos": [
        "11962"
      ],
      "status": "Vendido"
    },
    {
      "id": "166136",
      "IAM_dominio_id": "310",
      "IAM_unidade_id": "320",
      "IAM_usuario_id": "7704",
      "VIA_cliente_id": "118",
      "datahora_cadastro": "2023-05-15 15:02:31",
      "datahora_desativacao": null,
      "nome": "TESTE - Canto L 11",
      "descricao": "",
      "observacao": "",
      "orcamentos": [
        "11963"
      ],
      "status": "Vendido"
    },
    {
      "id": "166137",
      "IAM_dominio_id": "310",
      "IAM_unidade_id": "320",
      "IAM_usuario_id": "7704",
      "VIA_cliente_id": "118",
      "datahora_cadastro": "2023-05-15 15:21:51",
      "datahora_desativacao": null,
      "nome": "TESTE - Canto L 12",
      "descricao": "",
      "observacao": "",
      "orcamentos": [
        "11964"
      ],
      "status": "Vendido"
    },
    {
      "id": "166138",
      "IAM_dominio_id": "310",
      "IAM_unidade_id": "320",
      "IAM_usuario_id": "7704",
      "VIA_cliente_id": "118",
      "datahora_cadastro": "2023-05-15 15:27:10",
      "datahora_desativacao": null,
      "nome": "TESTE - canto L 13",
      "descricao": "",
      "observacao": "",
      "orcamentos": [
        "11965"
      ],
      "status": "Vendido"
    },
    {
      "id": "166142",
      "IAM_dominio_id": "310",
      "IAM_unidade_id": "320",
      "IAM_usuario_id": "7704",
      "VIA_cliente_id": "118",
      "datahora_cadastro": "2023-05-15 17:22:22",
      "datahora_desativacao": null,
      "nome": "TESTE - canto L 14",
      "descricao": "",
      "observacao": "",
      "orcamentos": [
        "11969"
      ],
      "status": "Vendido"
    },
    {
      "id": "166143",
      "IAM_dominio_id": "310",
      "IAM_unidade_id": "320",
      "IAM_usuario_id": "7704",
      "VIA_cliente_id": "118",
      "datahora_cadastro": "2023-05-15 17:26:04",
      "datahora_desativacao": null,
      "nome": "TESTE - Canto L 15",
      "descricao": "",
      "observacao": "",
      "orcamentos": [
        "11970"
      ],
      "status": "Vendido"
    }
  ]
}
